simpleBlackScholes/__init__.py
simpleBlackScholes/main.py
simpleBlackScholes/utils.py
simpleBlackScholes-1.0.2.dist-info/METADATA
simpleBlackScholes-1.0.2.dist-info/WHEEL
simpleBlackScholes-1.0.2.dist-info/top_level.txt
simpleBlackScholes-1.0.2.dist-info/RECORD
