Metadata-Version: 2.1
Name: simpleBlackScholes
Version: 1.0.2
Summary: Functions for Black-Scholes Model related calculations.
Author: Anas Arkawi
Requires-Python: >=3.11
Requires-Dist: numpy
Requires-Dist: pandas
Requires-Dist: dataclasses
Requires-Dist: pydantic
Requires-Dist: scipy
